setup.cfg
setup.py
extra/apache/sitegen.conf
extra/bash/sitegen
extra/sitegen/sitegen.json
extra/sitegen/hooks-available/cert/000-print
extra/sitegen/hooks-available/cert/100-mkwebroot
extra/sitegen/hooks-available/cert/200-reload
extra/sitegen/hooks-available/site/000-print
extra/sitegen/hooks-available/site/100-sitegen-cert-request
extra/sitegen/hooks-available/site/200-chown
extra/sitegen/hooks-available/site/300-a2ensite
extra/sitegen/hooks-available/site/400-reload
extra/sitegen/templates/default.include
extra/sitegen/templates/docker.include
extra/sitegen/templates/http.conf
extra/sitegen/templates/https.conf
extra/sitegen/templates/laravel.include
extra/sitegen/templates/reverse.include
extra/sitegen/templates/rhttp.conf
extra/sitegen/templates/rhttps.conf
extra/sitegen/templates/sreverse.include
sitegencli/__init__.py
sitegencli/sitegen.py
sitegencli.egg-info/PKG-INFO
sitegencli.egg-info/SOURCES.txt
sitegencli.egg-info/dependency_links.txt
sitegencli.egg-info/entry_points.txt
sitegencli.egg-info/requires.txt
sitegencli.egg-info/top_level.txt