Metadata-Version: 1.1
Name: sitegencli
Version: 1.0.0
Summary: CLI tool to build web site configuration
Home-page: https://git.rthoni.com/robin.thoni/sitegen
Author: Robin Thoni
Author-email: robin@rthoni.com
License: MIT
Keywords: certbot apache ssl
Platform: UNKNOWN
Classifier: Development Status :: 5 - Production/Stable
Classifier: Intended Audience :: System Administrators
Classifier: Topic :: Internet :: WWW/HTTP :: HTTP Servers
Classifier: License :: OSI Approved :: MIT License
Classifier: Programming Language :: Python :: 3
Classifier: Programming Language :: Python :: 3.3
Classifier: Programming Language :: Python :: 3.4
Classifier: Programming Language :: Python :: 3.5
